dht_pi/Raspberry_Pi_Driver.cpython-312-aarch64-linux-gnu.so
dht_pi/__init__.py
dht_pi/reading.py
dht_pi/sensor.py
dht_pi/sensors.py
dht_pi-0.1.3.dist-info/METADATA
dht_pi-0.1.3.dist-info/WHEEL
dht_pi-0.1.3.dist-info/top_level.txt
dht_pi-0.1.3.dist-info/RECORD
dht_pi-0.1.3.dist-info/licenses/LICENSE
