Metadata-Version: 2.4
Name: dht-pi
Version: 0.1.3
Summary: DHT11, DHT22, and AM2302 temperature and humidity sensor reading library for Raspberry Pi
Author-email: Emir Karamehmetoglu <ek2660@gmail.com>
License: MIT
Project-URL: Homepage, https://github.com/emirkmo/dht-pi
Project-URL: Repository, https://github.com/emirkmo/dht-pi
Project-URL: Issues, https://github.com/emirkmo/dht-pi/issues
Classifier: Development Status :: 4 - Beta
Classifier: Operating System :: POSIX :: Linux
Classifier: License :: OSI Approved :: MIT License
Classifier: Intended Audience :: Developers
Classifier: Programming Language :: Python :: 3
Classifier: Topic :: Software Development
Classifier: Topic :: System :: Hardware
Requires-Python: >=3.11
License-File: LICENSE
Dynamic: license-file
